greenstack.so
greenstack-0.6.dist-info/metadata.json
greenstack-0.6.dist-info/WHEEL
greenstack-0.6.dist-info/RECORD
greenstack-0.6.dist-info/DESCRIPTION.rst
greenstack-0.6.dist-info/METADATA
greenstack-0.6.dist-info/top_level.txt
greenstack-0.6.data/headers/greenstack.h
